neptune_cli/__init__.py
neptune_cli/auth.py
neptune_cli/cli.py
neptune_cli/client.py
neptune_cli/config.py
neptune_cli/mcp.py
neptune_cli/mcp_instructions.md
neptune_common/__init__.py
neptune_common/models.py
test_fussybeaver_neptune_cli-0.1.15.dist-info/METADATA
test_fussybeaver_neptune_cli-0.1.15.dist-info/WHEEL
test_fussybeaver_neptune_cli-0.1.15.dist-info/entry_points.txt
test_fussybeaver_neptune_cli-0.1.15.dist-info/RECORD
