Metadata-Version: 2.4
Name: test-fussybeaver-neptune-cli
Version: 0.1.15
Summary: CLI for Neptune (neptune.dev)
Author: Neptune CLI contributors
Maintainer: Neptune
Keywords: cli,cloud,deployment,devops,ifc,infrastructure
Classifier: Development Status :: 3 - Alpha
Classifier: Environment :: Console
Classifier: Intended Audience :: Developers
Classifier: Natural Language :: English
Classifier: Operating System :: OS Independent
Classifier: Programming Language :: Python :: 3.13
Classifier: Topic :: System :: Software Distribution
Requires-Python: >=3.13
Requires-Dist: click>=8.1.0
Requires-Dist: fastmcp>=2.13.0.2
Requires-Dist: loguru>=0.7.3
Requires-Dist: platformdirs>=4.5.0
Requires-Dist: pydantic-settings>=2.11.0
Requires-Dist: requests>=2.32.5
Provides-Extra: dev
Requires-Dist: pytest; extra == 'dev'
